rtl/core/sign_extend.v
module sign_extend(
input [15:0] imm,
output [31:0] imm_ext
);

assign imm_ext = {{16{imm[15]}}, imm};

endmodule

rtl/memory/dmem.v
module dmem(
input clk,
input mem_write,
input [31:0] address,
input [31:0] write_data,
output [31:0] read_data
);
reg [31:0] memory [0:255];
assign read_data = memory[address[31:2]];
always @(posedge clk) begin
	if(mem_write)
memory[address[31:2]] <= write_data;
end

endmodule

rtl/core/alu.v
module alu(
input [31:0] a,
input [31:0] b,
input [2:0] alucontrol,
output reg [31:0] result);
always @(*) begin
	case(alucontrol)
3'b000:
    result = a + b;
3'b001:
result = a - b;
3'b010:
     result = a & b;
3'b011:
  result = a | b;
3'b100:
result = a ^ b;
3'b101:
    result = (a < b) ? 32'd1 : 32'd0;

    default:
     result = 32'd0;

    endcase

end

endmodule

rtl/core/regfile.v
module register(
input clk,
input reg_write,

input [4:0] read_reg1,
input [4:0] read_reg2,

input [4:0] write_reg,
input [31:0] write_data,

output [31:0] read_data1,
output [31:0] read_data2
);

reg [31:0] registers [0:31];

integer i;

initial begin

        for(i = 0; i < 32; i = i + 1)

                registers[i] = 32'b0;

end

assign read_data1 = registers[read_reg1];

assign read_data2 = registers[read_reg2];

always @(posedge clk) begin

        if(reg_write && write_reg != 0)

                registers[write_reg] <= write_data;

end

endmodule

rtl/core/control_unit.v
module control_unit(
input [5:0] opcode,
input [5:0] funct,
output reg alu_src,
output reg branch,
output reg mem_to_reg,
output reg reg_dst,
output reg mem_write,
output reg reg_write,
output reg jump,
output reg [2:0] alucontrol
);

always @(*) begin
	reg_dst = 0;
	mem_to_reg = 0;
        reg_write = 0;
        mem_write = 0;
	jump=0;
	alu_src = 0;
        alucontrol = 3'b000;
	branch = 0;
        case(opcode)

6'b000000: begin
	reg_dst = 1;
        reg_write = 1;

        case(funct)

6'b100000:
        alucontrol = 3'b000;

6'b100010:
        alucontrol = 3'b001;

6'b100100:
        alucontrol = 3'b010;

6'b100101:
        alucontrol = 3'b011;

6'b100110:
        alucontrol = 3'b100;

6'b101010:
        alucontrol = 3'b101;

default:
        alucontrol = 3'b000;

        endcase

end

6'b101011: begin

        mem_write = 1;
	alu_src = 1;
        alucontrol = 3'b000;

end
6'b100011: begin

        reg_write = 1;
	alu_src = 1;
        mem_to_reg = 1;

        alucontrol = 3'b000;

end
6'b001000: begin

        reg_write = 1;

        alu_src = 1;

        reg_dst = 0;

        alucontrol = 3'b000;

end
6'b000100: begin

        branch = 1;

        alucontrol = 3'b001;

end
6'b000010: begin

        jump = 1;

end

default: begin
	mem_to_reg = 0;
        reg_write = 0;
        mem_write = 0;
        alucontrol = 3'b000;

end

        endcase

end
   
endmodule

rtl/core/instruction_decode.v
module decode(input [31:0] instruction,
output [4:0] rs,
output [4:0] rt,
output [4:0] rd,
output [5:0] func,
output [5:0] opcode,
output [15:0] imm,
output [4:0] shamt,
output [25:0] addr);
assign opcode = instruction[31:26];
assign rs = instruction[25:21];
assign rt = instruction[20:16];
assign rd = instruction[15:11];
assign shamt = instruction[10:6];
assign func = instruction[5:0];
assign imm = instruction[15:0];
assign addr = instruction[25:0];
endmodule

rtl/top/execute_stage.v
module execute_stage(
input clk,
input [31:0] pc_curr,
input [31:0] instruction,
output branch_taken,
output [31:0] branch_target,
output [31:0] alu_result,
output jump,
output [31:0] jump_target
);
wire [2:0] alucontrol;
wire reg_write;
wire mem_write;
wire mem_to_reg;
wire [4:0] rs;
wire [4:0] rt;
wire [4:0] rd;
wire alu_src;
wire [31:0] imm_ext;
wire [31:0] alu_input_b;
wire [5:0] func;
wire [5:0] opcode;
wire branch;
wire [31:0] branch_offset;
wire [15:0] imm;

wire [31:0] pc_plus_4;
wire [4:0] shamt;
wire [31:0] writeback_data;
wire [25:0] addr;
wire [31:0] mem_read_data;
wire [31:0] read_data1;
wire [31:0] read_data2;
wire reg_dst;

wire [4:0] write_reg;
wire [31:0] alu_write_result;
decode decode_hard(
.instruction(instruction),
.rs(rs),
.rt(rt),
.rd(rd),
.func(func),
.opcode(opcode),
.imm(imm),
.shamt(shamt),
.addr(addr)
);
control_unit control_hard(
.reg_dst(reg_dst),
.opcode(opcode),
.alu_src(alu_src),
.funct(func),
.reg_write(reg_write),
.mem_write(mem_write),
.mem_to_reg(mem_to_reg),
.branch(branch),
.jump(jump),
.alucontrol(alucontrol)
);
register register_hard(
.clk(clk),
.reg_write(reg_write),

.read_reg1(rs),
.read_reg2(rt),

.write_reg(write_reg),
.write_data(writeback_data),

.read_data1(read_data1),
.read_data2(read_data2)
);

alu alu_hard(
.a(read_data1),
.b(alu_input_b),
.alucontrol(alucontrol),
.result(alu_write_result)
);
dmem dmem_hard(.clk(clk),

.mem_write(mem_write),

.address(alu_write_result),

.write_data(read_data2),

.read_data(mem_read_data)
);
sign_extend sign_extend_hard(
.imm(imm),
.imm_ext(imm_ext)
);

assign alu_result = alu_write_result;
assign writeback_data =
(mem_to_reg) ? mem_read_data : alu_write_result;
assign alu_input_b =
(alu_src) ? imm_ext : read_data2;
assign write_reg =
(reg_dst) ? rd : rt;
assign branch_taken =
(branch && (alu_write_result == 0));
assign branch_offset = imm_ext << 2;
assign branch_target =
pc_curr + 4 + branch_offset;
assign pc_plus_4 = pc_curr + 4;
assign jump_target =
(jump === 1'b1) ?
{pc_plus_4[31:28], addr, 2'b00} :
32'b0;
endmodule

rtl/memory/imem.v
module imem(
input [31:0] address,
output reg [31:0] instruction
);

always @(*) begin

        case(address)
32'h00000000:
instruction = 32'h20080005;

32'h00000004:
instruction = 32'h20090003;

32'h00000008:
instruction = 32'h08000005;

32'h0000000C:
instruction = 32'h200A0001;

32'h00000014:
instruction = 32'h200B0009;

default:
instruction = 32'h20000000;

        endcase

end

endmodule

rtl/core/pc.v
module pc(
input clk,
input reset,
input [31:0] pc_next,
output reg [31:0] pc_curr);
always @(posedge clk) begin
	if(reset)
		pc_curr <= 32'b0;
	else
		pc_curr <=pc_next;
end
endmodule

rtl/top/if_stage.v
module if_stage(input clk,
input reset,
input jump,
input [31:0] jump_target,
input branch_taken,
input [31:0] branch_target,
output [31:0] instruction,
output [31:0] pc);
wire [31:0] pc_curr;
wire [31:0] pc_next;
pc pc_hard(
.clk(clk),
.reset(reset),
.pc_next(pc_next),
.pc_curr(pc_curr));
imem imem_hard(
    .address(pc_curr),
    .instruction(instruction)
);
assign pc_next =
(jump === 1'b1) ? jump_target :
(branch_taken === 1'b1) ? branch_target :
(pc_curr + 4);
assign pc=pc_curr;
endmodule

rtl/top/cpu.v
module cpu(
input clk,
input reset
);
wire jump;

wire [31:0] jump_target;
wire [31:0] instruction;
wire [31:0] pc;
wire branch_taken;
wire [31:0] branch_target;
wire [31:0] alu_result;

if_stage if_hard(.clk(clk),
.reset(reset),
.branch_taken(branch_taken),
.branch_target(branch_target),
.instruction(instruction),
.pc(pc),
.jump(jump),
.jump_target(jump_target)
);

execute_stage execute_hard(.clk(clk),
.instruction(instruction),
.pc_curr(pc),
.branch_taken(branch_taken),
.branch_target(branch_target),
.alu_result(alu_result),
.jump(jump),
.jump_target(jump_target)
);

endmodule

tb/cpu_tb.v
module cpu_tb;

reg clk;

reg reset;

cpu dut(
.clk(clk),
.reset(reset)
);

always #5 clk = ~clk;

initial begin

$dumpfile("waveforms/cpu.vcd");
$dumpvars(0, cpu_tb);

clk = 0;

reset = 1;

#10;

reset = 0;

#100;

$finish;

end

endmodule

waveforms/cpu.vcd
$date
	Sat May  9 10:28:03 2026
$end
$version
	Icarus Verilog
$end
$timescale
	1s
$end
$scope module cpu_tb $end
$var reg 1 ! clk $end
$var reg 1 " reset $end
$scope module dut $end
$var wire 1 ! clk $end
$var wire 1 " reset $end
$var wire 32 # pc [31:0] $end
$var wire 32 $ jump_target [31:0] $end
$var wire 1 % jump $end
$var wire 32 & instruction [31:0] $end
$var wire 32 ' branch_target [31:0] $end
$var wire 1 ( branch_taken $end
$var wire 32 ) alu_result [31:0] $end
$scope module execute_hard $end
$var wire 32 * alu_result [31:0] $end
$var wire 1 ( branch_taken $end
$var wire 1 ! clk $end
$var wire 32 + writeback_data [31:0] $end
$var wire 5 , write_reg [4:0] $end
$var wire 5 - shamt [4:0] $end
$var wire 5 . rt [4:0] $end
$var wire 5 / rs [4:0] $end
$var wire 1 0 reg_write $end
$var wire 1 1 reg_dst $end
$var wire 32 2 read_data2 [31:0] $end
$var wire 32 3 read_data1 [31:0] $end
$var wire 5 4 rd [4:0] $end
$var wire 32 5 pc_plus_4 [31:0] $end
$var wire 32 6 pc_curr [31:0] $end
$var wire 6 7 opcode [5:0] $end
$var wire 1 8 mem_write $end
$var wire 1 9 mem_to_reg $end
$var wire 32 : mem_read_data [31:0] $end
$var wire 32 ; jump_target [31:0] $end
$var wire 1 % jump $end
$var wire 32 < instruction [31:0] $end
$var wire 32 = imm_ext [31:0] $end
$var wire 16 > imm [15:0] $end
$var wire 6 ? func [5:0] $end
$var wire 32 @ branch_target [31:0] $end
$var wire 32 A branch_offset [31:0] $end
$var wire 1 B branch $end
$var wire 3 C alucontrol [2:0] $end
$var wire 32 D alu_write_result [31:0] $end
$var wire 1 E alu_src $end
$var wire 32 F alu_input_b [31:0] $end
$var wire 26 G addr [25:0] $end
$scope module alu_hard $end
$var wire 32 H b [31:0] $end
$var wire 3 I alucontrol [2:0] $end
$var wire 32 J a [31:0] $end
$var reg 32 K result [31:0] $end
$upscope $end
$scope module control_hard $end
$var wire 6 L opcode [5:0] $end
$var wire 6 M funct [5:0] $end
$var reg 1 E alu_src $end
$var reg 3 N alucontrol [2:0] $end
$var reg 1 B branch $end
$var reg 1 % jump $end
$var reg 1 9 mem_to_reg $end
$var reg 1 8 mem_write $end
$var reg 1 1 reg_dst $end
$var reg 1 0 reg_write $end
$upscope $end
$scope module decode_hard $end
$var wire 5 O shamt [4:0] $end
$var wire 5 P rt [4:0] $end
$var wire 5 Q rs [4:0] $end
$var wire 5 R rd [4:0] $end
$var wire 6 S opcode [5:0] $end
$var wire 32 T instruction [31:0] $end
$var wire 16 U imm [15:0] $end
$var wire 6 V func [5:0] $end
$var wire 26 W addr [25:0] $end
$upscope $end
$scope module dmem_hard $end
$var wire 32 X address [31:0] $end
$var wire 1 ! clk $end
$var wire 1 8 mem_write $end
$var wire 32 Y read_data [31:0] $end
$var wire 32 Z write_data [31:0] $end
$upscope $end
$scope module register_hard $end
$var wire 1 ! clk $end
$var wire 32 [ read_data1 [31:0] $end
$var wire 32 \ read_data2 [31:0] $end
$var wire 5 ] read_reg1 [4:0] $end
$var wire 5 ^ read_reg2 [4:0] $end
$var wire 1 0 reg_write $end
$var wire 32 _ write_data [31:0] $end
$var wire 5 ` write_reg [4:0] $end
$var integer 32 a i [31:0] $end
$upscope $end
$scope module sign_extend_hard $end
$var wire 16 b imm [15:0] $end
$var wire 32 c imm_ext [31:0] $end
$upscope $end
$upscope $end
$scope module if_hard $end
$var wire 1 ( branch_taken $end
$var wire 32 d branch_target [31:0] $end
$var wire 1 ! clk $end
$var wire 1 % jump $end
$var wire 32 e jump_target [31:0] $end
$var wire 32 f pc [31:0] $end
$var wire 1 " reset $end
$var wire 32 g pc_next [31:0] $end
$var wire 32 h pc_curr [31:0] $end
$var wire 32 i instruction [31:0] $end
$scope module imem_hard $end
$var wire 32 j address [31:0] $end
$var reg 32 k instruction [31:0] $end
$upscope $end
$scope module pc_hard $end
$var wire 1 ! clk $end
$var wire 32 l pc_next [31:0] $end
$var wire 1 " reset $end
$var reg 32 m pc_curr [31:0] $end
$upscope $end
$upscope $end
$upscope $end
$upscope $end
$enddefinitions $end
$comment Show the parameter values. $end
$dumpall
$end
#0
$dumpvars
b0 m
b100 l
b100000000010000000000000000101 k
b0 j
b100000000010000000000000000101 i
b0 h
b100 g
b0 f
b0 e
b11000 d
b101 c
b101 b
b100000 a
b1000 `
b101 _
b1000 ^
b0 ]
b0 \
b0 [
b0 Z
bx Y
b101 X
b10000000000000000101 W
b101 V
b101 U
b100000000010000000000000000101 T
b1000 S
b0 R
b0 Q
b1000 P
b0 O
b0 N
b101 M
b1000 L
b101 K
b0 J
b0 I
b101 H
b10000000000000000101 G
b101 F
1E
b101 D
b0 C
0B
b10100 A
b11000 @
b101 ?
b101 >
b101 =
b100000000010000000000000000101 <
b0 ;
bx :
09
08
b1000 7
b0 6
b100 5
b0 4
b0 3
b0 2
01
10
b0 /
b1000 .
b0 -
b1000 ,
b101 +
b101 *
b101 )
0(
b11000 '
b100000000010000000000000000101 &
0%
b0 $
b0 #
1"
0!
$end
#5
b101 2
b101 Z
b101 \
1!
#10
0!
0"
#15
b11 +
b11 _
b11 )
b11 *
b11 D
b11 K
b11 X
b1100 A
b11 F
b11 H
1E
10
b1001 ,
b1001 `
b1000 g
b1000 l
b10010000000000000011 G
b10010000000000000011 W
b11 =
b11 c
b11 >
b11 U
b11 b
b11 ?
b11 M
b11 V
b0 2
b0 Z
b0 \
b1001 .
b1001 P
b1001 ^
b100000000010010000000000000011 &
b100000000010010000000000000011 <
b100000000010010000000000000011 T
b100000000010010000000000000011 i
b100000000010010000000000000011 k
b1000 5
b10100 '
b10100 @
b10100 d
b100 #
b100 6
b100 f
b100 h
b100 j
b100 m
1!
#20
0!
#25
b0 +
b0 _
b0 )
b0 *
b0 D
b0 K
b0 X
b10100 $
b10100 ;
b10100 e
b10100 A
b0 F
b0 H
b0 ,
b0 `
1%
0E
00
b10100 g
b10100 l
b101 G
b101 W
b101 =
b101 c
b101 >
b101 U
b101 b
b101 ?
b101 M
b101 V
b0 .
b0 P
b0 ^
b10 7
b10 L
b10 S
b1000000000000000000000000101 &
b1000000000000000000000000101 <
b1000000000000000000000000101 T
b1000000000000000000000000101 i
b1000000000000000000000000101 k
b0 2
b0 Z
b0 \
b1100 5
b100000 '
b100000 @
b100000 d
b1000 #
b1000 6
b1000 f
b1000 h
b1000 j
b1000 m
1!
#30
0!
#35
b1001 +
b1001 _
b1001 )
b1001 *
b1001 D
b1001 K
b1001 X
b1001 F
b1001 H
b11000 g
b11000 l
b0 $
b0 ;
b0 e
b100100 A
b1011 ,
b1011 `
1E
10
0%
b10110000000000001001 G
b10110000000000001001 W
b1001 =
b1001 c
b1001 >
b1001 U
b1001 b
b1001 ?
b1001 M
b1001 V
b1011 .
b1011 P
b1011 ^
b1000 7
b1000 L
b1000 S
b100000000010110000000000001001 &
b100000000010110000000000001001 <
b100000000010110000000000001001 T
b100000000010110000000000001001 i
b100000000010110000000000001001 k
b11000 5
b111100 '
b111100 @
b111100 d
b10100 #
b10100 6
b10100 f
b10100 h
b10100 j
b10100 m
1!
#40
0!
#45
b0 +
b0 _
b0 )
b0 *
b0 D
b0 K
b0 X
b0 A
b0 F
b0 H
1E
10
b0 ,
b0 `
b11100 g
b11100 l
b0 G
b0 W
b0 =
b0 c
b0 >
b0 U
b0 b
b0 ?
b0 M
b0 V
b0 .
b0 P
b0 ^
b100000000000000000000000000000 &
b100000000000000000000000000000 <
b100000000000000000000000000000 T
b100000000000000000000000000000 i
b100000000000000000000000000000 k
b0 2
b0 Z
b0 \
b11100 5
b11100 '
b11100 @
b11100 d
b11000 #
b11000 6
b11000 f
b11000 h
b11000 j
b11000 m
1!
#50
0!
#55
b100000 g
b100000 l
b100000 5
b100000 '
b100000 @
b100000 d
b11100 #
b11100 6
b11100 f
b11100 h
b11100 j
b11100 m
1!
#60
0!
#65
b100100 g
b100100 l
b100100 5
b100100 '
b100100 @
b100100 d
b100000 #
b100000 6
b100000 f
b100000 h
b100000 j
b100000 m
1!
#70
0!
#75
b101000 g
b101000 l
b101000 5
b101000 '
b101000 @
b101000 d
b100100 #
b100100 6
b100100 f
b100100 h
b100100 j
b100100 m
1!
#80
0!
#85
b101100 g
b101100 l
b101100 5
b101100 '
b101100 @
b101100 d
b101000 #
b101000 6
b101000 f
b101000 h
b101000 j
b101000 m
1!
#90
0!
#95
b110000 g
b110000 l
b110000 5
b110000 '
b110000 @
b110000 d
b101100 #
b101100 6
b101100 f
b101100 h
b101100 j
b101100 m
1!
#100
0!
#105
b110100 g
b110100 l
b110100 5
b110100 '
b110100 @
b110100 d
b110000 #
b110000 6
b110000 f
b110000 h
b110000 j
b110000 m
1!
