rtl/core/sign_extend.v
module sign_extend(
input [15:0] imm,
output [31:0] imm_ext
);

assign imm_ext = {{16{imm[15]}}, imm};

endmodule

rtl/memory/dmem.v
module dmem(
input clk,
input mem_write,
input [31:0] address,
input [31:0] write_data,
output [31:0] read_data
);
reg [31:0] memory [0:255];
assign read_data = memory[address[31:2]];
always @(posedge clk) begin
	if(mem_write)
memory[address[31:2]] <= write_data;
end

endmodule

rtl/core/alu.v
module alu(
input [31:0] a,
input [31:0] b,
input [2:0] alucontrol,
output reg [31:0] result);
always @(*) begin
	case(alucontrol)
3'b000:
    result = a + b;
3'b001:
result = a - b;
3'b010:
     result = a & b;
3'b011:
  result = a | b;
3'b100:
result = a ^ b;
3'b101:
    result = (a < b) ? 32'd1 : 32'd0;

    default:
     result = 32'd0;

    endcase

end

endmodule

rtl/core/regfile.v
module register(
input clk,
input reg_write,

input [4:0] read_reg1,
input [4:0] read_reg2,

input [4:0] write_reg,
input [31:0] write_data,

output [31:0] read_data1,
output [31:0] read_data2
);

reg [31:0] registers [0:31];

integer i;

initial begin

        for(i = 0; i < 32; i = i + 1)

                registers[i] = 32'b0;

end

assign read_data1 = registers[read_reg1];

assign read_data2 = registers[read_reg2];

always @(posedge clk) begin

        if(reg_write && write_reg != 0)

                registers[write_reg] <= write_data;

end

endmodule

rtl/core/control_unit.v
module control_unit(
input [5:0] opcode,
input [5:0] funct,
output reg alu_src,
output reg branch,
output reg mem_to_reg,
output reg reg_dst,
output reg mem_write,
output reg reg_write,
output reg [2:0] alucontrol
);

always @(*) begin
	reg_dst = 0;
	mem_to_reg = 0;
        reg_write = 0;
        mem_write = 0;
	alu_src = 0;
        alucontrol = 3'b000;
	branch = 0;
        case(opcode)

6'b000000: begin
	reg_dst = 1;
        reg_write = 1;

        case(funct)

6'b100000:
        alucontrol = 3'b000;

6'b100010:
        alucontrol = 3'b001;

6'b100100:
        alucontrol = 3'b010;

6'b100101:
        alucontrol = 3'b011;

6'b100110:
        alucontrol = 3'b100;

6'b101010:
        alucontrol = 3'b101;

default:
        alucontrol = 3'b000;

        endcase

end

6'b101011: begin

        mem_write = 1;
	alu_src = 1;
        alucontrol = 3'b000;

end
6'b100011: begin

        reg_write = 1;
	alu_src = 1;
        mem_to_reg = 1;

        alucontrol = 3'b000;

end
6'b001000: begin

        reg_write = 1;

        alu_src = 1;

        reg_dst = 0;

        alucontrol = 3'b000;

end
6'b000100: begin

        branch = 1;

        alucontrol = 3'b001;

end

default: begin
	mem_to_reg = 0;
        reg_write = 0;
        mem_write = 0;
        alucontrol = 3'b000;

end

        endcase

end
   
endmodule

rtl/core/instruction_decode.v
module decode(input [31:0] instruction,
output [4:0] rs,
output [4:0] rt,
output [4:0] rd,
output [5:0] func,
output [5:0] opcode,
output [15:0] imm,
output [4:0] shamt,
output [25:0] addr);
assign opcode = instruction[31:26];
assign rs = instruction[25:21];
assign rt = instruction[20:16];
assign rd = instruction[15:11];
assign shamt = instruction[10:6];
assign func = instruction[5:0];
assign imm = instruction[15:0];
assign addr = instruction[25:0];
endmodule

rtl/top/execute_stage.v
module execute_stage(
input clk,
input [31:0] pc_curr,
input [31:0] instruction,
output branch_taken,
output [31:0] branch_target,
output [31:0] alu_result
);
wire [2:0] alucontrol;
wire reg_write;
wire mem_write;
wire mem_to_reg;
wire [4:0] rs;
wire [4:0] rt;
wire [4:0] rd;
wire alu_src;
wire [31:0] imm_ext;
wire [31:0] alu_input_b;
wire [5:0] func;
wire [5:0] opcode;
wire branch;
wire [31:0] branch_offset;
wire [15:0] imm;

wire [4:0] shamt;
wire [31:0] writeback_data;
wire [25:0] addr;
wire [31:0] mem_read_data;
wire [31:0] read_data1;
wire [31:0] read_data2;
wire reg_dst;

wire [4:0] write_reg;
wire [31:0] alu_write_result;
decode decode_hard(
.instruction(instruction),
.rs(rs),
.rt(rt),
.rd(rd),
.func(func),
.opcode(opcode),
.imm(imm),
.shamt(shamt),
.addr(addr)
);
control_unit control_hard(
.reg_dst(reg_dst),
.opcode(opcode),
.alu_src(alu_src),
.funct(func),
.reg_write(reg_write),
.mem_write(mem_write),
.mem_to_reg(mem_to_reg),
.branch(branch),
.alucontrol(alucontrol)
);
register register_hard(
.clk(clk),
.reg_write(reg_write),

.read_reg1(rs),
.read_reg2(rt),

.write_reg(write_reg),
.write_data(writeback_data),

.read_data1(read_data1),
.read_data2(read_data2)
);

alu alu_hard(
.a(read_data1),
.b(alu_input_b),
.alucontrol(alucontrol),
.result(alu_write_result)
);
dmem dmem_hard(.clk(clk),

.mem_write(mem_write),

.address(alu_write_result),

.write_data(read_data2),

.read_data(mem_read_data)
);
sign_extend sign_extend_hard(
.imm(imm),
.imm_ext(imm_ext)
);

assign alu_result = alu_write_result;
assign writeback_data =
(mem_to_reg) ? mem_read_data : alu_write_result;
assign alu_input_b =
(alu_src) ? imm_ext : read_data2;
assign write_reg =
(reg_dst) ? rd : rt;
assign branch_taken =
(branch && (alu_write_result == 0));
assign branch_offset = imm_ext << 2;
assign branch_target =
pc_curr + 4 + branch_offset;
endmodule

rtl/memory/imem.v
module imem(
input [31:0] address,
output reg [31:0] instruction
);

always @(*) begin

        case(address)

32'h00000000:
instruction = 32'h20080005;

32'h00000004:
instruction = 32'h20090005;

32'h00000008:
instruction = 32'h11090001;

32'h0000000C:
instruction = 32'h200A0001;

32'h00000010:
instruction = 32'h200B0009;

default:
instruction = 32'h20000000;

        endcase

end

endmodule

rtl/core/pc.v
module pc(
input clk,
input reset,
input [31:0] pc_next,
output reg [31:0] pc_curr
);

always @(posedge clk or posedge reset) begin

        if(reset)
                pc_curr <= 32'b0;

        else
                pc_curr <= pc_next;

end

endmodule

rtl/top/if_stage.v
module if_stage(input clk,
input reset,
input branch_taken,
input [31:0] branch_target,
output [31:0] instruction,
output [31:0] pc);
wire [31:0] pc_curr;
wire [31:0] pc_next;
pc pc_hard(
.clk(clk),
.reset(reset),
.pc_next(pc_next),
.pc_curr(pc_curr));
imem imem_hard(
    .address(pc_curr),
    .instruction(instruction)
);
assign pc_next =
(branch_taken) ? branch_target : (pc_curr + 4);
assign pc = pc_curr;
endmodule

rtl/top/cpu.v
module cpu(
input clk,
input reset
);

wire [31:0] instruction;
wire [31:0] pc;
wire branch_taken;
wire [31:0] branch_target;
wire [31:0] alu_result;

if_stage if_hard(.clk(clk),
.reset(reset),
.branch_taken(branch_taken),
.branch_target(branch_target),
.instruction(instruction),
.pc(pc)
);

execute_stage execute_hard(.clk(clk),
.instruction(instruction),
.pc_curr(pc),
.branch_taken(branch_taken),
.branch_target(branch_target),
.alu_result(alu_result)
);

endmodule

tb/cpu_tb.v
module cpu_tb;

reg clk;

reg reset;

cpu dut(
.clk(clk),
.reset(reset)
);

always #5 clk = ~clk;

initial begin

$dumpfile("waveforms/cpu.vcd");
$dumpvars(0, cpu_tb);

clk = 0;

reset = 1;

#10;

reset = 0;

#100;

$finish;

end

endmodule

waveforms/cpu.vcd
$date
	Sat May  9 09:56:18 2026
$end
$version
	Icarus Verilog
$end
$timescale
	1s
$end
$scope module cpu_tb $end
$var reg 1 ! clk $end
$var reg 1 " reset $end
$scope module dut $end
$var wire 1 ! clk $end
$var wire 1 " reset $end
$var wire 32 # pc [31:0] $end
$var wire 32 $ instruction [31:0] $end
$var wire 32 % branch_target [31:0] $end
$var wire 1 & branch_taken $end
$var wire 32 ' alu_result [31:0] $end
$scope module execute_hard $end
$var wire 32 ( alu_result [31:0] $end
$var wire 1 & branch_taken $end
$var wire 1 ! clk $end
$var wire 32 ) writeback_data [31:0] $end
$var wire 5 * write_reg [4:0] $end
$var wire 5 + shamt [4:0] $end
$var wire 5 , rt [4:0] $end
$var wire 5 - rs [4:0] $end
$var wire 1 . reg_write $end
$var wire 1 / reg_dst $end
$var wire 32 0 read_data2 [31:0] $end
$var wire 32 1 read_data1 [31:0] $end
$var wire 5 2 rd [4:0] $end
$var wire 32 3 pc_curr [31:0] $end
$var wire 6 4 opcode [5:0] $end
$var wire 1 5 mem_write $end
$var wire 1 6 mem_to_reg $end
$var wire 32 7 mem_read_data [31:0] $end
$var wire 32 8 instruction [31:0] $end
$var wire 32 9 imm_ext [31:0] $end
$var wire 16 : imm [15:0] $end
$var wire 6 ; func [5:0] $end
$var wire 32 < branch_target [31:0] $end
$var wire 32 = branch_offset [31:0] $end
$var wire 1 > branch $end
$var wire 3 ? alucontrol [2:0] $end
$var wire 32 @ alu_write_result [31:0] $end
$var wire 1 A alu_src $end
$var wire 32 B alu_input_b [31:0] $end
$var wire 26 C addr [25:0] $end
$scope module alu_hard $end
$var wire 32 D b [31:0] $end
$var wire 3 E alucontrol [2:0] $end
$var wire 32 F a [31:0] $end
$var reg 32 G result [31:0] $end
$upscope $end
$scope module control_hard $end
$var wire 6 H opcode [5:0] $end
$var wire 6 I funct [5:0] $end
$var reg 1 A alu_src $end
$var reg 3 J alucontrol [2:0] $end
$var reg 1 > branch $end
$var reg 1 6 mem_to_reg $end
$var reg 1 5 mem_write $end
$var reg 1 / reg_dst $end
$var reg 1 . reg_write $end
$upscope $end
$scope module decode_hard $end
$var wire 5 K shamt [4:0] $end
$var wire 5 L rt [4:0] $end
$var wire 5 M rs [4:0] $end
$var wire 5 N rd [4:0] $end
$var wire 6 O opcode [5:0] $end
$var wire 32 P instruction [31:0] $end
$var wire 16 Q imm [15:0] $end
$var wire 6 R func [5:0] $end
$var wire 26 S addr [25:0] $end
$upscope $end
$scope module dmem_hard $end
$var wire 32 T address [31:0] $end
$var wire 1 ! clk $end
$var wire 1 5 mem_write $end
$var wire 32 U read_data [31:0] $end
$var wire 32 V write_data [31:0] $end
$upscope $end
$scope module register_hard $end
$var wire 1 ! clk $end
$var wire 32 W read_data1 [31:0] $end
$var wire 32 X read_data2 [31:0] $end
$var wire 5 Y read_reg1 [4:0] $end
$var wire 5 Z read_reg2 [4:0] $end
$var wire 1 . reg_write $end
$var wire 32 [ write_data [31:0] $end
$var wire 5 \ write_reg [4:0] $end
$var integer 32 ] i [31:0] $end
$upscope $end
$scope module sign_extend_hard $end
$var wire 16 ^ imm [15:0] $end
$var wire 32 _ imm_ext [31:0] $end
$upscope $end
$upscope $end
$scope module if_hard $end
$var wire 1 & branch_taken $end
$var wire 32 ` branch_target [31:0] $end
$var wire 1 ! clk $end
$var wire 32 a pc [31:0] $end
$var wire 1 " reset $end
$var wire 32 b pc_next [31:0] $end
$var wire 32 c pc_curr [31:0] $end
$var wire 32 d instruction [31:0] $end
$scope module imem_hard $end
$var wire 32 e address [31:0] $end
$var reg 32 f instruction [31:0] $end
$upscope $end
$scope module pc_hard $end
$var wire 1 ! clk $end
$var wire 32 g pc_next [31:0] $end
$var wire 1 " reset $end
$var reg 32 h pc_curr [31:0] $end
$upscope $end
$upscope $end
$upscope $end
$upscope $end
$enddefinitions $end
$comment Show the parameter values. $end
$dumpall
$end
#0
$dumpvars
b0 h
b100 g
b100000000010000000000000000101 f
b0 e
b100000000010000000000000000101 d
b0 c
b100 b
b0 a
b11000 `
b101 _
b101 ^
b100000 ]
b1000 \
b101 [
b1000 Z
b0 Y
b0 X
b0 W
b0 V
bx U
b101 T
b10000000000000000101 S
b101 R
b101 Q
b100000000010000000000000000101 P
b1000 O
b0 N
b0 M
b1000 L
b0 K
b0 J
b101 I
b1000 H
b101 G
b0 F
b0 E
b101 D
b10000000000000000101 C
b101 B
1A
b101 @
b0 ?
0>
b10100 =
b11000 <
b101 ;
b101 :
b101 9
b100000000010000000000000000101 8
bx 7
06
05
b1000 4
b0 3
b0 2
b0 1
b0 0
0/
1.
b0 -
b1000 ,
b0 +
b1000 *
b101 )
b101 (
b101 '
0&
b11000 %
b100000000010000000000000000101 $
b0 #
1"
0!
$end
#5
b101 0
b101 V
b101 X
1!
#10
0!
0"
#15
b1001 *
b1001 \
b10010000000000000101 C
b10010000000000000101 S
b0 0
b0 V
b0 X
b1001 ,
b1001 L
b1001 Z
b1000 b
b1000 g
b100000000010010000000000000101 $
b100000000010010000000000000101 8
b100000000010010000000000000101 P
b100000000010010000000000000101 d
b100000000010010000000000000101 f
b11100 %
b11100 <
b11100 `
b100 #
b100 3
b100 a
b100 c
b100 e
b100 h
1!
#20
0!
#25
b0 )
b0 [
1&
b100 =
b0 '
b0 (
b0 @
b0 G
b0 T
b1 ?
b1 E
b1 J
1>
0A
0.
b1000010010000000000000001 C
b1000010010000000000000001 S
b1 9
b1 _
b1 :
b1 Q
b1 ^
b1 ;
b1 I
b1 R
b101 1
b101 F
b101 W
b1000 -
b1000 M
b1000 Y
b100 4
b100 H
b100 O
b10000 b
b10000 g
b10001000010010000000000000001 $
b10001000010010000000000000001 8
b10001000010010000000000000001 P
b10001000010010000000000000001 d
b10001000010010000000000000001 f
b101 0
b101 V
b101 X
b10000 %
b10000 <
b10000 `
b1000 #
b1000 3
b1000 a
b1000 c
b1000 e
b1000 h
1!
#30
0!
#35
b1001 )
b1001 [
0&
b100100 =
b1001 B
b1001 D
b1011 *
b1011 \
b1001 '
b1001 (
b1001 @
b1001 G
b1001 T
1A
1.
0>
b0 ?
b0 E
b0 J
b10110000000000001001 C
b10110000000000001001 S
b1001 9
b1001 _
b1001 :
b1001 Q
b1001 ^
b1001 ;
b1001 I
b1001 R
b0 0
b0 V
b0 X
b1011 ,
b1011 L
b1011 Z
b0 1
b0 F
b0 W
b0 -
b0 M
b0 Y
b1000 4
b1000 H
b1000 O
b10100 b
b10100 g
b100000000010110000000000001001 $
b100000000010110000000000001001 8
b100000000010110000000000001001 P
b100000000010110000000000001001 d
b100000000010110000000000001001 f
b111000 %
b111000 <
b111000 `
b10000 #
b10000 3
b10000 a
b10000 c
b10000 e
b10000 h
1!
#40
0!
#45
b0 )
b0 [
b0 '
b0 (
b0 @
b0 G
b0 T
b0 =
b0 B
b0 D
1A
1.
b0 *
b0 \
b0 C
b0 S
b0 9
b0 _
b0 :
b0 Q
b0 ^
b0 ;
b0 I
b0 R
b0 ,
b0 L
b0 Z
b11000 b
b11000 g
b100000000000000000000000000000 $
b100000000000000000000000000000 8
b100000000000000000000000000000 P
b100000000000000000000000000000 d
b100000000000000000000000000000 f
b0 0
b0 V
b0 X
b11000 %
b11000 <
b11000 `
b10100 #
b10100 3
b10100 a
b10100 c
b10100 e
b10100 h
1!
#50
0!
#55
b11100 b
b11100 g
b11100 %
b11100 <
b11100 `
b11000 #
b11000 3
b11000 a
b11000 c
b11000 e
b11000 h
1!
#60
0!
#65
b100000 b
b100000 g
b100000 %
b100000 <
b100000 `
b11100 #
b11100 3
b11100 a
b11100 c
b11100 e
b11100 h
1!
#70
0!
#75
b100100 b
b100100 g
b100100 %
b100100 <
b100100 `
b100000 #
b100000 3
b100000 a
b100000 c
b100000 e
b100000 h
1!
#80
0!
#85
b101000 b
b101000 g
b101000 %
b101000 <
b101000 `
b100100 #
b100100 3
b100100 a
b100100 c
b100100 e
b100100 h
1!
#90
0!
#95
b101100 b
b101100 g
b101100 %
b101100 <
b101100 `
b101000 #
b101000 3
b101000 a
b101000 c
b101000 e
b101000 h
1!
#100
0!
#105
b110000 b
b110000 g
b110000 %
b110000 <
b110000 `
b101100 #
b101100 3
b101100 a
b101100 c
b101100 e
b101100 h
1!
