rtl/memory/imem.v
module imem(
input [31:0] address,
output reg [31:0] instruction
);

always @(*) begin

        case(address)

32'h00000000:
instruction = 32'h20080005;

32'h00000004:
instruction = 32'h20090005;

32'h00000008:
instruction = 32'h11090001;

32'h0000000C:
instruction = 32'h200A0001;

32'h00000010:
instruction = 32'h200B0009;

default:
instruction = 32'h00000000;

        endcase

end

endmodule

rtl/core/pc.v
module pc(
input clk,
input reset,
input [31:0] pc_next,
output reg [31:0] pc_curr);
always @(posedge clk) begin
	if(reset)
		pc_curr <= 32'b0;
	else
		pc_curr <=pc_next;
end
endmodule

rtl/top/if_stage.v
module if_stage(input clk,
input reset,
output [31:0] instruction,
output [31:0] pc);
wire [31:0] pc_curr;
wire [31:0] pc_next;
pc pc_hard(
.clk(clk),
.reset(reset),
.pc_next(pc_next),
.pc_curr(pc_curr));
imem imem_hard(
    .address(pc_curr),
    .instruction(instruction)
);
assign pc_next = pc_curr + 4;
assign pc = pc_curr;
endmodule

tb/if_stage_tb.v
module if_stage_tb;
reg clk;
reg reset;
wire [31:0] instruction;
wire [31:0] pc;
if_stage dut(
    .clk(clk),
    .reset(reset),
    .instruction(instruction),
    .pc(pc)
);
always #5 clk = ~clk;
initial begin
    $dumpfile("waveforms/if_stage.vcd");
    $dumpvars(0, if_stage_tb);
    clk = 0;
    reset = 1;
    #10;
    reset = 0;
    #50;
    $finish;
end
endmodule

waveforms/if_stage.vcd
$date
	Fri May  8 04:26:10 2026
$end
$version
	Icarus Verilog
$end
$timescale
	1s
$end
$scope module if_stage_tb $end
$var wire 32 ! pc [31:0] $end
$var wire 32 " instruction [31:0] $end
$var reg 1 # clk $end
$var reg 1 $ reset $end
$scope module dut $end
$var wire 1 # clk $end
$var wire 32 % pc [31:0] $end
$var wire 1 $ reset $end
$var wire 32 & pc_next [31:0] $end
$var wire 32 ' pc_curr [31:0] $end
$var wire 32 ( instruction [31:0] $end
$scope module imem_hard $end
$var wire 32 ) instruction [31:0] $end
$var wire 32 * address [31:0] $end
$upscope $end
$scope module pc_hard $end
$var wire 1 # clk $end
$var wire 32 + pc_next [31:0] $end
$var wire 1 $ reset $end
$var reg 32 , pc_curr [31:0] $end
$upscope $end
$upscope $end
$upscope $end
$enddefinitions $end
$comment Show the parameter values. $end
$dumpall
$end
#0
$dumpvars
bx ,
bx +
bx *
bx )
bx (
bx '
bx &
bx %
1$
0#
bx "
bx !
$end
#5
b100000000010000000000000000101 "
b100000000010000000000000000101 (
b100000000010000000000000000101 )
b100 &
b100 +
b0 !
b0 %
b0 '
b0 *
b0 ,
1#
#10
0#
0$
#15
b100000000010010000000000000011 "
b100000000010010000000000000011 (
b100000000010010000000000000011 )
b1000 &
b1000 +
b100 !
b100 %
b100 '
b100 *
b100 ,
1#
#20
0#
#25
b1000010010101000000100000 "
b1000010010101000000100000 (
b1000010010101000000100000 )
b1100 &
b1100 +
b1000 !
b1000 %
b1000 '
b1000 *
b1000 ,
1#
#30
0#
#35
bx "
bx (
bx )
b10000 &
b10000 +
b1100 !
b1100 %
b1100 '
b1100 *
b1100 ,
1#
#40
0#
#45
b10100 &
b10100 +
b10000 !
b10000 %
b10000 '
b10000 *
b10000 ,
1#
#50
0#
#55
b11000 &
b11000 +
b10100 !
b10100 %
b10100 '
b10100 *
b10100 ,
1#
