rtl/core/pc.v
module pc(
input clk,
input reset,
input [31:0] pc_next,
output reg [31:0] pc_curr);
always @(posedge clk) begin
	if(reset)
		pc_curr <= 32'b0;
	else
		pc_curr <=pc_next;
end
endmodule

tb/pc_tb.v
module pc_tb;

reg clk;
reg reset;
reg [31:0] pc_next;

wire [31:0] pc_curr;

pc dut(
    .clk(clk),
    .reset(reset),
    .pc_next(pc_next),
    .pc_curr(pc_curr)
);

always #5 clk = ~clk;

initial begin

    $dumpfile("waveforms/pc.vcd");
    $dumpvars(0, pc_tb);

    clk = 0;
    reset = 1;
    pc_next = 32'd0;

    #10;
    reset = 0;

    #10;
    pc_next = 32'd4;

    #10;
    pc_next = 32'd8;

    #10;
    pc_next = 32'd12;

    #20;

    $finish;

end

endmodule

waveforms/pc.vcd
$date
	Fri May  8 03:48:54 2026
$end
$version
	Icarus Verilog
$end
$timescale
	1s
$end
$scope module pc_tb $end
$var wire 32 ! pc_curr [31:0] $end
$var reg 1 " clk $end
$var reg 32 # pc_next [31:0] $end
$var reg 1 $ reset $end
$scope module dut $end
$var wire 1 " clk $end
$var wire 32 % pc_next [31:0] $end
$var wire 1 $ reset $end
$var reg 32 & pc_curr [31:0] $end
$upscope $end
$upscope $end
$enddefinitions $end
$comment Show the parameter values. $end
$dumpall
$end
#0
$dumpvars
bx &
b0 %
1$
b0 #
0"
bx !
$end
#5
b0 !
b0 &
1"
#10
0"
0$
#15
1"
#20
0"
b100 #
b100 %
#25
b100 !
b100 &
1"
#30
0"
b1000 #
b1000 %
#35
b1000 !
b1000 &
1"
#40
0"
b1100 #
b1100 %
#45
b1100 !
b1100 &
1"
